AutoImblearn/__init__.py
AutoImblearn/config.py
AutoImblearn/exceptions.py
AutoImblearn/main.py
AutoImblearn/metrics.py
AutoImblearn/components/__init__.py
AutoImblearn/components/exceptions.py
AutoImblearn/components/api/__init__.py
AutoImblearn/components/api/base_estimator_api.py
AutoImblearn/components/api/base_model_api.py
AutoImblearn/components/api/base_survival_estimator_api.py
AutoImblearn/components/api/base_transformer_api.py
AutoImblearn/components/api/base_unsupervised_estimator_api.py
AutoImblearn/components/automls/__init__.py
AutoImblearn/components/automls/autosklearn/__init__.py
AutoImblearn/components/automls/autosklearn/run.py
AutoImblearn/components/automls/autosklearn/Docker/__init__.py
AutoImblearn/components/automls/autosklearn/Docker/app.py
AutoImblearn/components/automls/h2o/__init__.py
AutoImblearn/components/automls/h2o/run.py
AutoImblearn/components/automls/h2o/Docker/__init__.py
AutoImblearn/components/automls/h2o/Docker/app.py
AutoImblearn/components/automls/tpot/__init__.py
AutoImblearn/components/automls/tpot/run.py
AutoImblearn/components/automls/tpot/Docker/__init__.py
AutoImblearn/components/automls/tpot/Docker/app.py
AutoImblearn/components/classifiers/__init__.py
AutoImblearn/components/classifiers/_sklearnbased/__init__.py
AutoImblearn/components/classifiers/_sklearnbased/run.py
AutoImblearn/components/classifiers/_sklearnbased/Docker/__init__.py
AutoImblearn/components/classifiers/_sklearnbased/Docker/app.py
AutoImblearn/components/classifiers/_xgboostbased/__init__.py
AutoImblearn/components/classifiers/_xgboostbased/run.py
AutoImblearn/components/classifiers/_xgboostbased/Docker/__init__.py
AutoImblearn/components/classifiers/_xgboostbased/Docker/app.py
AutoImblearn/components/hybrids/__init__.py
AutoImblearn/components/hybrids/autorsp/__init__.py
AutoImblearn/components/hybrids/autorsp/run.py
AutoImblearn/components/hybrids/autosmote/__init__.py
AutoImblearn/components/hybrids/autosmote/run.py
autoimblearn-0.3.24.dist-info/licenses/LICENSE
autoimblearn-0.3.24.dist-info/METADATA
autoimblearn-0.3.24.dist-info/WHEEL
autoimblearn-0.3.24.dist-info/top_level.txt
autoimblearn-0.3.24.dist-info/RECORD
