Metadata-Version: 2.4
Name: AutoImblearn
Version: 0.3.24
Summary: Automated machine learning system for imbalanced medical data with survival analysis, unsupervised learning, and hyperparameter optimization
Author: Hank Wang
Author-email: hankwang1991@gmail.com
License: BSD 3-Clause License
Keywords: medical analysis,automated machine learning
Classifier: Development Status :: 3 - Alpha
Classifier: Programming Language :: Python :: 3
Classifier: Programming Language :: Python :: 3.9
Classifier: Programming Language :: Python :: 3.10
Classifier: License :: OSI Approved :: MIT License
Classifier: Operating System :: OS Independent
Classifier: Intended Audience :: Science/Research
Classifier: Topic :: Scientific/Engineering :: Artificial Intelligence
Requires-Python: >=3.9
License-File: LICENSE
Requires-Dist: docker
Requires-Dist: joblib
Requires-Dist: pandas
Requires-Dist: scikit-learn
Requires-Dist: pydantic
Requires-Dist: gensim
Requires-Dist: flask
Requires-Dist: optuna>=3.0.0
Provides-Extra: web
Requires-Dist: matplotlib; extra == "web"
Requires-Dist: seaborn; extra == "web"
Provides-Extra: imputer
Requires-Dist: hyperimpute; extra == "imputer"
Provides-Extra: resampler
Requires-Dist: smote_variants; extra == "resampler"
Requires-Dist: imbalanced-learn; extra == "resampler"
Provides-Extra: survival
Requires-Dist: scikit-survival>=0.22.0; extra == "survival"
Provides-Extra: unsupervised
Requires-Dist: umap-learn; extra == "unsupervised"
Provides-Extra: r-model
Requires-Dist: rpy2; extra == "r-model"
Provides-Extra: dev
Requires-Dist: check-manifest; extra == "dev"
Dynamic: author
Dynamic: author-email
Dynamic: classifier
Dynamic: description
Dynamic: description-content-type
Dynamic: keywords
Dynamic: license
Dynamic: license-file
Dynamic: provides-extra
Dynamic: requires-dist
Dynamic: requires-python
Dynamic: summary
